<root type="0" typeName="View" time="0" x="0" y="0" width="704" height="100" visible="true" fillParentWidth="false" fillParentHeight="false" nodeAlign="8" isGenerateLocal="false">
  <bg type="1" typeName="Image" time="0" x="0" y="0" width="691" height="98" visible="true" fillParentWidth="false" fillParentHeight="false" nodeAlign="8" file="d6b9163b065219ba211d341d7a598bf4" packFile="" gridLeft="0" gridRight="0" gridTop="0" gridBottom="0" varname="bg">
    <detailButton type="1" typeName="Button" time="0" x="13" y="8" width="454" height="85" visible="true" fillParentWidth="false" fillParentHeight="false" nodeAlign="8" file="c28eae11be2f8dbe1e6e7308aaa9fd97" file2="c28eae11be2f8dbe1e6e7308aaa9fd97" packFile="" gridLeft="0" gridRight="0" gridTop="0" gridBottom="0" varname="detailButton" callbackfunc="onDetailButtonClick"/>
    <buyButton type="1" typeName="Button" time="0" x="12" y="9" width="677" height="82" visible="true" fillParentWidth="false" fillParentHeight="false" nodeAlign="8" file="c28eae11be2f8dbe1e6e7308aaa9fd97" file2="7902683df58f8a39106f50ec783f94c0" packFile="" gridLeft="0" gridRight="0" gridTop="0" gridBottom="0" varname="buyButton" callbackfunc="onBuyButtonClick"/>
    <pointImage type="1" typeName="Image" time="0" x="15" y="48" width="35" height="28" visible="false" fillParentWidth="false" fillParentHeight="false" nodeAlign="8" file="4d39aceba12e6bff7390044227ed497c" packFile="" gridLeft="0" gridRight="0" gridTop="0" gridBottom="0" varname="pointImage"/>
    <hotImage type="1" typeName="Image" time="0" x="11" y="14" width="56" height="56" visible="false" fillParentWidth="false" fillParentHeight="false" nodeAlign="8" file="ddbd134c22b17e29eb1845034a507546" packFile="" gridLeft="0" gridRight="0" gridTop="0" gridBottom="0" varname="hotImage"/>
    <goosIcon type="1" typeName="Image" time="0" x="-271" y="0" width="77" height="41" visible="true" fillParentWidth="false" fillParentHeight="false" nodeAlign="0" file="f7e0101b7c3719ba96aee01187e6f395" packFile="" gridLeft="0" gridRight="0" gridTop="0" gridBottom="0" varname="goosIcon"/>
    <Text_rate_add type="4" typeName="Text" time="0" x="299" y="25" width="124" height="29" visible="false" fillParentWidth="false" fillParentHeight="false" nodeAlign="8" fontName="" fontSize="20" textAlign="7" color="0x00f5ff" string="Text" colorA="1" varname="Text_rate_add"/>
    <Text_gold type="4" typeName="Text" time="0" x="155" y="23" width="36" height="31" visible="false" fillParentWidth="false" fillParentHeight="false" nodeAlign="8" fontName="" fontSize="20" textAlign="7" color="0xFFFFFF" string="Text" colorA="1" varname="Text_gold"/>
    <goodsMoneyLabel type="4" typeName="Text" time="0" x="153" y="32" width="123" height="35" visible="true" fillParentWidth="false" fillParentHeight="false" nodeAlign="8" fontName="" fontSize="32" textAlign="7" color="0x1ee2f4" string="0" varname="goodsMoneyLabel" colorA="1"/>
    <changeMoneyLabel type="4" typeName="Text" time="0" x="375" y="42" width="45" height="18" visible="true" fillParentWidth="false" fillParentHeight="false" nodeAlign="8" fontName="" fontSize="20" textAlign="0" color="0xFFFFFF" string="0" colorA="1" varname="changeMoneyLabel"/>
    <payMoneyLabel type="4" typeName="Text" time="0" x="542" y="27" width="146" height="48" visible="true" fillParentWidth="false" fillParentHeight="false" nodeAlign="8" fontName="" fontSize="24" textAlign="7" color="0xFFFFFF" string="0" colorA="1" varname="payMoneyLabel"/>
    <goldImage type="1" typeName="Image" time="0" x="508" y="35" width="31" height="29" visible="false" fillParentWidth="false" fillParentHeight="false" nodeAlign="8" file="487e9fe8cc6f2cdd0823a2811952212e" packFile="" gridLeft="0" gridRight="0" gridTop="0" gridBottom="0" varname="goldImage"/>
    <detailLabel type="4" typeName="Text" time="0" x="0" y="20" width="644" height="64" visible="true" fillParentWidth="false" fillParentHeight="false" nodeAlign="5" fontName="" fontSize="18" textAlign="0" color="0xFFFFFF" varname="detailLabel" colorA="1"/>
  </bg>
</root>